washing_machine.v
`timescale 1ns/1ns
module washing_machine (clock,reset,door_close,start,filled,detergent_added,
        cycle_timeout,drained,spin_timeout,door_lock,motor_on,fill_valve_on,
        drain_valve_on,done,soap_wash,water_wash);
input clock,reset,door_close,start,filled,detergent_added,cycle_timeout,drained,spin_timeout;
output reg door_lock,motor_on,fill_valve_on,drain_valve_on,done,soap_wash,water_wash;

parameter check_door = 3'b000;
parameter fill_water = 3'b001;
parameter add_detergent = 3'b010;
parameter cycle = 3'b011;
parameter drain_water = 3'b100;
parameter spin = 3'b101;
reg [2:0]current_state,next_state;

always @(current_state or start or door_close or filled or detergent_added
         or drained or cycle_timeout or spin_timeout) 
         begin
           case (current_state)
            check_door : if (start == 1 && door_close == 1) 
                         begin
                           next_state = fill_water;
                           motor_on = 0;
                           fill_valve_on = 0;
                           drain_valve_on = 0;
                           door_lock = 1;
                           water_wash = 0;
                           soap_wash = 0;
                           done = 0;
                         end
                         else 
                         begin
                            next_state = current_state;
                            motor_on = 0;
                            fill_valve_on = 0;
                            drain_valve_on = 0;
                            door_lock = 0;
                            water_wash = 0;
                            soap_wash = 0;
                            done = 0;
                         end
            fill_water : if (filled) 
                         begin
                           if (soap_wash == 0) 
                           begin
                             next_state = add_detergent;
                             motor_on = 0;
                             fill_valve_on = 0;
                             drain_valve_on = 0;
                             door_lock = 1;
                             soap_wash = 1;
                             water_wash = 0;
                             done = 0; 
                           end
                           else
                           begin
                            next_state = cycle;
                            motor_on = 0;
                            fill_valve_on = 0;
                            drain_valve_on = 0;
                            door_lock = 1;
                            soap_wash = 1;
                            water_wash = 1;
                            done = 0;
                           end
                         end  
                         else
                           begin
                            next_state = current_state;
                            motor_on = 0;
                            fill_valve_on = 1;
                            drain_valve_on = 0;
                            door_lock =1;
                            done = 0;
                           end 
             add_detergent: if (detergent_added == 1) 
                            begin
                              next_state = cycle;
                              motor_on = 0;
                              fill_valve_on = 0;
                              drain_valve_on = 0;
                              door_lock = 1;
                              soap_wash = 1;
                              done = 0; 
                            end  
                            else
                            begin
                              next_state = current_state;
                              motor_on = 0;
                              fill_valve_on = 0;
                              door_lock = 1;
                              soap_wash = 1;
                              done = 0;
                            end 
             cycle : if (cycle_timeout == 1) 
                     begin
                      next_state = drain_water;
                      motor_on = 0;
                      fill_valve_on = 0;
                      drain_valve_on = 0;
                      door_lock = 1;
                      //soap_wash = 1;
                      done = 0;
                     end       
                     else
                     begin
                        next_state = current_state;
                        motor_on = 1;
                        fill_valve_on = 0;
                        drain_valve_on = 0;
                        door_lock = 1;
                        // soap_wash = 1;
                        done = 0;
                     end    
             drain_water : if (drained == 1) 
                           begin
                             if (water_wash == 0) 
                             begin
                               next_state = fill_water;
                               motor_on = 0;
                               fill_valve_on = 0;
                               drain_valve_on = 0;
                               door_lock = 1;
                               soap_wash = 1;
                               // water_wash = 1;
                               done = 0;     
                             end
                             else
                             begin
                                next_state = spin;
                                motor_on = 0;
                                fill_valve_on = 0;
                                drain_valve_on = 0;
                                door_lock = 1;
                                soap_wash = 1;
                                water_wash = 1;
                                done = 0;
                             end
                           end
                           else
                           begin
                            next_state = current_state;
                            motor_on = 0;
                            fill_valve_on = 0;
                            drain_valve_on = 1;
                            door_lock = 1;
                            soap_wash = 1;
                            // water_wash = 1;
                            done = 0;
                           end
             spin : if (spin_timeout == 1) 
                    begin
                      next_state = door_close;
                      motor_on = 0;
                      fill_valve_on = 0;
                      drain_valve_on = 0;
                      door_lock = 1;
                      soap_wash = 1;
                      water_wash = 1;
                      done = 1;
                    end
                    else
                    begin
                        next_state = current_state;
                        motor_on = 0;
                        fill_valve_on = 0;
                        drain_valve_on = 1;
                        door_lock = 1;
                        soap_wash = 1;
                        water_wash = 1;
                        done = 0;
                    end                          
            default: next_state = check_door; 
           endcase
         end

always @(posedge clock or negedge reset) 
begin
  if (reset) 
   current_state <= 3'b000;  
  else
    current_state <= next_state;    
end

endmodule

washing_machine_tb.v
`timescale 1ns/1ns
`include "washing_machine.v"
module washing_machine_tb;
  reg clock,reset,door_close,start,filled,detergent_added,cycle_timeout,drained,spin_timeout;
  wire door_lock,motor_on,fill_valve_on,drain_valve_on,done,soap_wash,water_wash;

  washing_machine m1(.clock(clock),.reset(reset),.door_close(door_close),
                     .start(start),.filled(filled),.detergent_added(detergent_added),
                     .cycle_timeout(cycle_timeout),.drained(drained),
                     .spin_timeout(spin_timeout),.door_lock(door_lock),
                     .motor_on(motor_on),.fill_valve_on(fill_valve_on),
                     .drain_valve_on(drain_valve_on),.done(done),
                     .soap_wash(soap_wash),.water_wash(water_wash));
  initial 
  begin
    $dumpfile("washing_machine.vcd");
    $dumpvars(0,washing_machine_tb);
    clock = 0;
    forever #5 clock = ~clock; 
  end   

  initial 
  begin
    reset = 1;
    start = 0;
    door_close = 0;
    filled = 0;
    drained = 0;
    detergent_added = 0;
    cycle_timeout = 0;
    spin_timeout = 0;
    #5 reset = 0;
    #5 start = 1; door_close = 1;
    #10 filled = 1;
    #10 detergent_added = 1;
    #10 cycle_timeout = 1;
    #10 drained = 1;
    #10 spin_timeout = 1;
    #40 $finish;  
  end         

  initial
	begin
		$monitor("Time=%0d, Clock=%b, Reset=%b, start=%b, door_close=%b, filled=%b, detergent_added=%b, cycle_timeout=%b, drained=%b, spin_timeout=%b, door_lock=%b, motor_on=%b, fill_valve_on=%b, drain_valve_on=%b, soap_wash=%b, water_wash=%b, done=%b",$time, clock, reset, start, door_close, filled, detergent_added, cycle_timeout, drained, spin_timeout, door_lock, motor_on, fill_valve_on, drain_valve_on, soap_wash, water_wash, done);
	end       
endmodule

washing_machine.vcd
$date
	Thu Jul 18 01:42:39 2024
$end
$version
	Icarus Verilog
$end
$timescale
	1ns
$end
$scope module washing_machine_tb $end
$var wire 1 ! water_wash $end
$var wire 1 " soap_wash $end
$var wire 1 # motor_on $end
$var wire 1 $ fill_valve_on $end
$var wire 1 % drain_valve_on $end
$var wire 1 & door_lock $end
$var wire 1 ' done $end
$var reg 1 ( clock $end
$var reg 1 ) cycle_timeout $end
$var reg 1 * detergent_added $end
$var reg 1 + door_close $end
$var reg 1 , drained $end
$var reg 1 - filled $end
$var reg 1 . reset $end
$var reg 1 / spin_timeout $end
$var reg 1 0 start $end
$scope module m1 $end
$var wire 1 ( clock $end
$var wire 1 ) cycle_timeout $end
$var wire 1 * detergent_added $end
$var wire 1 + door_close $end
$var wire 1 , drained $end
$var wire 1 - filled $end
$var wire 1 . reset $end
$var wire 1 / spin_timeout $end
$var wire 1 0 start $end
$var reg 3 1 current_state [2:0] $end
$var reg 1 ' done $end
$var reg 1 & door_lock $end
$var reg 1 % drain_valve_on $end
$var reg 1 $ fill_valve_on $end
$var reg 1 # motor_on $end
$var reg 3 2 next_state [2:0] $end
$var reg 1 " soap_wash $end
$var reg 1 ! water_wash $end
$upscope $end
$upscope $end
$enddefinitions $end
#0
$dumpvars
b0 2
bx 1
00
0/
1.
0-
0,
0+
0*
0)
0(
x'
x&
x%
x$
x#
x"
x!
$end
#5
0'
0"
0!
0&
0%
0$
0#
b0 1
0.
1(
#10
1&
b1 2
1+
10
0(
#15
1$
b1 1
1(
#20
1"
0$
b10 2
0(
1-
#25
b10 1
1(
#30
b11 2
0(
1*
#35
1#
b11 1
1(
#40
0#
b100 2
0(
1)
#45
1%
b100 1
1(
#50
0%
b1 2
0(
1,
#55
1!
b11 2
b1 1
1(
#60
0(
1/
#65
b100 2
b11 1
1(
#70
0(
#75
b101 2
b100 1
1(
#80
0(
#85
1'
b1 2
b101 1
1(
#90
0(
#95
0'
b11 2
b1 1
1(
